apscale_blast/__init__.py
apscale_blast/__main__.py
apscale_blast/a_blastn.py
apscale_blast/b_filter.py
apscale_blast-1.3.1.dist-info/LICENSE
apscale_blast-1.3.1.dist-info/METADATA
apscale_blast-1.3.1.dist-info/WHEEL
apscale_blast-1.3.1.dist-info/entry_points.txt
apscale_blast-1.3.1.dist-info/top_level.txt
apscale_blast-1.3.1.dist-info/RECORD
